<?xml version="1.0" encoding="UTF-8"?><ServiceComplementaire xmlns:dc="http://purl.org/dc/elements/1.1/" xmlns:xsi="http://www.w3.org/2001/XMLSchema-instance" ID="R14361" type="Formulaire" xsi:noNamespaceSchemaLocation="../Schemas/3.4/ServiceComplementaire.xsd" spUrl="https://www.service-public.fr/professionnels-entreprises/vosdroits/R14361"><dc:title>Demande administrative : préparation phytopharmaceutique (Formulaire 11906*02)</dc:title><dc:creator>Direction de l'information légale et administrative</dc:creator><dc:description>Demande administrative : préparation phytopharmaceutique - Formulaire</dc:description><dc:publisher>Direction de l'information légale et administrative</dc:publisher><dc:contributor>Direction de l'information légale et administrative (Premier ministre)</dc:contributor><dc:date>modified 2016-09-22</dc:date><dc:type>Formulaire</dc:type><dc:format>text/xml</dc:format><dc:identifier>R14361</dc:identifier><dc:language>Fr</dc:language><dc:coverage>France entière</dc:coverage><dc:rights>https://www.service-public.fr/a-propos/mentions-legales</dc:rights><SurTitre>Formulaire</SurTitre><Audience>Professionnels</Audience><Canal>www.service-public.fr</Canal><FilDAriane><Niveau ID="Professionnels">Accueil professionnels</Niveau><Niveau ID="servicesEnLigne" type="Liste - Service en ligne">Services en ligne et formulaires</Niveau><Niveau ID="R14361" type="Formulaire">Demande administrative : préparation phytopharmaceutique</Niveau></FilDAriane><NumeroCerfa>11906*02</NumeroCerfa><LienWeb URL="https://www.formulaires.service-public.fr/gf/cerfa_11906.do" format="application/pdf" poids="37.5 KB"><Source>Ministère chargé de l'agriculture</Source></LienWeb><NoticeLiee ID="R14362" URL="https://www.formulaires.service-public.fr/gf/getNotice.do?cerfaFormulaire=11906&amp;cerfaNotice=50850" type="Notice" numerocerfa="50854#02" format="application/pdf" poids="121.2 KB">Notice pour la demande administrative de préparation phytopharmaceutique</NoticeLiee><ServiceEnLigneAnnexe type="Formulaire" numerocerfa="11909*02" groupe="facultatif"><Titre>Préparation phytopharmaceutique : usages revendiqués</Titre><LienWeb URL="https://www.formulaires.service-public.fr/gf/cerfa_11909.do" format="application/pdf" poids="12.7 KB"/></ServiceEnLigneAnnexe><ServiceEnLigneAnnexe type="Formulaire" numerocerfa="11910*02" groupe="facultatif"><Titre>Préparation phytopharmaceutique : fiche technique usage mineur</Titre><LienWeb URL="https://www.formulaires.service-public.fr/gf/cerfa_11910.do" format="application/pdf" poids="21.9 KB"/></ServiceEnLigneAnnexe></ServiceComplementaire>