<?xml version="1.0" encoding="UTF-8"?><ServiceComplementaire xmlns:dc="http://purl.org/dc/elements/1.1/" xmlns:xsi="http://www.w3.org/2001/XMLSchema-instance" ID="R33069" type="Formulaire" xsi:noNamespaceSchemaLocation="../Schemas/3.4/ServiceComplementaire.xsd" spUrl="https://www.service-public.fr/professionnels-entreprises/vosdroits/R33069"><dc:title>Demande d'agrément ou de renouvellement d'agrément Maître exploitant agricole (Formulaire 11368*02)</dc:title><dc:creator>Direction de l'information légale et administrative</dc:creator><dc:description>Demande d'agrément ou de renouvellement d'agrément Maître exploitant agricole - Formulaire</dc:description><dc:publisher>Direction de l'information légale et administrative</dc:publisher><dc:contributor>Direction de l'information légale et administrative (Premier ministre)</dc:contributor><dc:date>modified 2018-01-04</dc:date><dc:type>Formulaire</dc:type><dc:format>text/xml</dc:format><dc:identifier>R33069</dc:identifier><dc:language>Fr</dc:language><dc:coverage>France entière</dc:coverage><dc:rights>https://www.service-public.fr/a-propos/mentions-legales</dc:rights><SurTitre>Formulaire</SurTitre><Audience>Professionnels</Audience><Canal>www.service-public.fr</Canal><FilDAriane><Niveau ID="Professionnels">Accueil professionnels</Niveau><Niveau ID="servicesEnLigne" type="Liste - Service en ligne">Services en ligne et formulaires</Niveau><Niveau ID="R33069" type="Formulaire">Demande d'agrément ou de renouvellement d'agrément Maître exploitant agricole</Niveau></FilDAriane><NumeroCerfa>11368*02</NumeroCerfa><LienWeb URL="https://www.formulaires.service-public.fr/gf/cerfa_11368.do" format="application/pdf" poids="121.7 KB"><Source>Ministère chargé de l'agriculture</Source></LienWeb><OuSAdresser ID="R35" sve="non" type="Local personnalisé sur SP"><Titre>Chambre d'agriculture</Titre><PivotLocal>chambre_agriculture</PivotLocal><RessourceWeb URL="https://chambres-agriculture.fr/chambres-dagriculture/nous-connaitre/lannuaire-des-chambres-dagriculture/"/><Source ID="R30771">Assemblée permanente des chambres d'agriculture (APCA)</Source></OuSAdresser></ServiceComplementaire>