<?xml version="1.0" encoding="UTF-8"?><Publication xmlns:dc="http://purl.org/dc/elements/1.1/" xmlns:xsi="http://www.w3.org/2001/XMLSchema-instance" ID="F2886" type="Fiche d'information conditionnée" xsi:noNamespaceSchemaLocation="../Schemas/3.4/Publication.xsd" dateDerniereModificationImportante="2019-12-26T00:00:00" spUrl="https://www.service-public.fr/particuliers/vosdroits/F2886"><dc:title>Drogue au volant</dc:title><dc:creator>Direction de l'information légale et administrative</dc:creator><dc:subject>Transports - Mobilité</dc:subject><dc:description>Quelles sont les sanctions en cas de conduite après usage de drogues (cannabis, ecstasy, cocaïne, LSD...) ? Quelle est la procédure de dépistage lors d'un contrôle routier ? Peut-on contester le résultat ? Nous vous indiquons les règles à connaître sur la drogue au volant.</dc:description><dc:publisher>Direction de l'information légale et administrative</dc:publisher><dc:contributor>Direction de l'information légale et administrative (Premier ministre)</dc:contributor><dc:date>modified 2023-06-13</dc:date><dc:type>Fiche pratique</dc:type><dc:format>text/xml</dc:format><dc:identifier>F2886</dc:identifier><dc:source>https://www.legifrance.gouv.fr/codes/section_lc/LEGITEXT000006074228/LEGISCTA000006159522, https://www.legifrance.gouv.fr/codes/id/LEGISCTA000006177151/, https://www.legifrance.gouv.fr/codes/id/LEGISCTA000006177152/, https://www.legifrance.gouv.fr/codes/section_lc/LEGITEXT000006070719/LEGISCTA000006165277/#LEGISCTA000006165277, https://www.legifrance.gouv.fr/codes/section_lc/LEGITEXT000006070719/LEGISCTA000006165280/, https://www.legifrance.gouv.fr/loda/id/JORFTEXT000000533085/, https://www.legifrance.gouv.fr/loda/id/JORFTEXT000033607271/</dc:source><dc:language>Fr</dc:language><dc:relation>isPartOf N18918</dc:relation><dc:coverage>France entière</dc:coverage><dc:rights>https://www.service-public.fr/a-propos/mentions-legales</dc:rights><SurTitre>Fiche pratique</SurTitre><Audience>Particuliers</Audience><Canal>www.service-public.fr</Canal><FilDAriane><Niveau ID="Particuliers">Accueil particuliers</Niveau><Niveau ID="N19812">Transports - Mobilité</Niveau><Niveau ID="N18918">Infractions routières</Niveau><Niveau ID="F2886" type="Fiche d'information conditionnée">Drogue au volant</Niveau></FilDAriane><Theme ID="N19812"><Titre>Transports - Mobilité</Titre></Theme><DossierPere ID="N18918"><Titre>Infractions routières</Titre><SousDossier ID="N18918-1"><Titre>Règles de sécurité routière</Titre><Fiche ID="F19460">Vitesse</Fiche><Fiche ID="F2886">Stupéfiants</Fiche><Fiche ID="F2881">Alcoolémie</Fiche></SousDossier><SousDossier ID="N18918-2"><Titre>Équipements obligatoires</Titre><Fiche ID="F19459">Voiture</Fiche><Fiche ID="F34168">Moto, scooter, 3 roues à moteur...</Fiche><Fiche ID="F34169">Vélo</Fiche></SousDossier><SousDossier ID="N18918-3"><Titre>Stationnement</Titre><Fiche ID="F34212">Stationnement gênant, dangereux, abusif</Fiche><Fiche ID="F34440">Stationnement non payé (forfait post-stationnement)</Fiche></SousDossier><SousDossier ID="N18918-4"><Titre>Sanctions concernant le conducteur</Titre><Fiche ID="F18509">Amende en cas de contravention</Fiche><Fiche ID="F31551">Barème des points retirés par infraction</Fiche><Fiche ID="F1685">Récupération des points</Fiche><Fiche ID="F14208">Stage de récupération des points</Fiche><Fiche ID="F1040">Rétention du permis</Fiche><Fiche ID="F1704">Invalidation (solde à zéro)</Fiche><Fiche ID="F14836">Suspension administrative</Fiche><Fiche ID="F21761">Suspension judiciaire</Fiche><Fiche ID="F21774">Annulation judiciaire</Fiche></SousDossier><SousDossier ID="N18918-5"><Titre>Sanctions concernant le véhicule</Titre><Fiche ID="F12914">Immobilisation d'un véhicule</Fiche><Fiche ID="F21887">Confiscation du véhicule</Fiche><Fiche ID="F12918">Mise en fourrière d'un véhicule</Fiche></SousDossier></DossierPere><SousDossierPere>Règles de sécurité routière</SousDossierPere><Introduction><Texte><Paragraphe>Quelles sont les sanctions en cas de conduite après usage de drogues (cannabis, ecstasy, cocaïne, <LienInterne LienPublication="R65189" type="Sigle">LSD</LienInterne>...) ? Quelle est la procédure de dépistage lors d'un contrôle routier ? Peut-on contester le résultat ? Nous vous indiquons les règles à connaître sur la drogue au volant.</Paragraphe></Texte></Introduction><Texte><Chapitre><Titre><Paragraphe>Peut-on conduire après avoir consommé de la drogue ?</Paragraphe></Titre><Paragraphe>Il est <MiseEnEvidence>interdit</MiseEnEvidence> de conduire après usage drogues (substances ou plantes classées comme stupéfiants) : cannabis, ecstasy, cocaïne, opiacés, <LienInterne LienPublication="R65189" type="Sigle">LSD</LienInterne>...</Paragraphe><Paragraphe>L'interdiction s'applique <MiseEnEvidence>quelle que soit la quantité</MiseEnEvidence> de drogue consommée.</Paragraphe><Paragraphe>En cas de <LienInterne LienPublication="F31901" type="Fiche Question-réponse conditionnée" audience="Particuliers">conduite accompagnée</LienInterne>, l'interdiction concerne également la <MiseEnEvidence>personne qui accompagne l'élève conducteur</MiseEnEvidence>.</Paragraphe><Complement><Titre>Connaître la liste des substances ou plantes classées comme stupéfiants</Titre><Paragraphe>Vous pouvez consulter la <MiseEnEvidence>liste actualisée</MiseEnEvidence> des substances ou plantes classées comme stupéfiants <LienExterne URL="https://www.legifrance.gouv.fr/loda/id/JORFTEXT000000533085">sur le site Légifrance</LienExterne>.</Paragraphe></Complement></Chapitre><Chapitre><Titre><Paragraphe>Dépistage de drogues : dans quelles situations ?</Paragraphe></Titre><Paragraphe>Le dépistage est <MiseEnEvidence>obligatoire</MiseEnEvidence> en cas <MiseEnEvidence>d'accident mortel</MiseEnEvidence> ou <MiseEnEvidence>corporel</MiseEnEvidence> (blessures) de la circulation.</Paragraphe><Paragraphe>Le <MiseEnEvidence>dépistage</MiseEnEvidence> est <MiseEnEvidence>facultatif</MiseEnEvidence> dans les cas suivants :</Paragraphe><Liste type="puce"><Item><Paragraphe>Vous êtes impliqué dans un <MiseEnEvidence>accident matériel de la circulation</MiseEnEvidence></Paragraphe></Item><Item><Paragraphe>Vous êtes <MiseEnEvidence>l'auteur présumé d'une <LienIntra LienID="R52094" type="Définition de glossaire">infraction</LienIntra> routière</MiseEnEvidence></Paragraphe></Item><Item><Paragraphe>Vous êtes <MiseEnEvidence>soupçonné avoir pris un stupéfiant</MiseEnEvidence></Paragraphe></Item></Liste><Paragraphe>Les forces de l'ordre (police, gendarmerie) ou le <LienIntra LienID="R1123" type="Définition de glossaire">procureur de la République</LienIntra> peuvent aussi décider de faire une <MiseEnEvidence>opération de dépistage de stupéfiants</MiseEnEvidence>.</Paragraphe></Chapitre><Chapitre><Titre><Paragraphe>Dépistage de drogues : quelle est la procédure ?</Paragraphe></Titre><SousChapitre><Titre><Paragraphe>Dépistage</Paragraphe></Titre><Paragraphe>Les forces de l'ordre utilisent un <MiseEnEvidence>test salivaire</MiseEnEvidence> pour <MiseEnEvidence>dépister</MiseEnEvidence> la consommation de drogues.</Paragraphe><Paragraphe>Il existe aussi un <MiseEnEvidence>test urinaire</MiseEnEvidence>, mais il est moins utilisé. Seul un médecin peut le faire.</Paragraphe><ASavoir><Titre>À savoir</Titre><Paragraphe>Si vous refusez de faire le test salivaire, ou s'il vous est impossible de le faire, un <MiseEnEvidence>prélèvement salivaire</MiseEnEvidence> ou <MiseEnEvidence>sanguin</MiseEnEvidence> est effectué.</Paragraphe></ASavoir></SousChapitre><SousChapitre><Titre><Paragraphe>Vérification</Paragraphe></Titre><Paragraphe>Si le <MiseEnEvidence>test</MiseEnEvidence> de dépistage est <MiseEnEvidence>positif</MiseEnEvidence>, les forces de l'ordre effectuent un <MiseEnEvidence>prélèvement salivaire</MiseEnEvidence> pour <MiseEnEvidence>vérifier</MiseEnEvidence> la consommation de drogues.</Paragraphe><Paragraphe>Les forces de l'ordre doivent vous demander <MiseEnEvidence>si vous souhaitez</MiseEnEvidence> vous réserver le droit de demander une <MiseEnEvidence>contre-expertise</MiseEnEvidence>.</Paragraphe><Paragraphe>En cas de réponse positive, un médecin réalise un <MiseEnEvidence>prélèvement sanguin</MiseEnEvidence> (prise de sang).</Paragraphe><Paragraphe>Ce prélèvement sanguin permet également de vérifier si vous prenez un <MiseEnEvidence>traitement médical</MiseEnEvidence>.</Paragraphe><Paragraphe>Le prélèvement salivaire ou sanguin est ensuite <MiseEnEvidence>analysé</MiseEnEvidence> par un laboratoire ou un expert agréé.</Paragraphe><Complement><Titre>Savoir comment demander une contre-expertise ou la recherche de l'usage de médicaments</Titre><Paragraphe>Pour demander une contre-expertise ou la recherche de l'usage de médicaments, vous devez indiquer, au moment du prélèvement salivaire, que vous souhaitez qu'un prélèvement sanguin soit réalisé.</Paragraphe><Paragraphe>Vous devez faire la demande dans un délai de <MiseEnEvidence>5 jours</MiseEnEvidence> suivant la <LienIntra LienID="R14732" type="Définition de glossaire">notification</LienIntra> du résultat de l'analyse du prélèvement salivaire ou sanguin.</Paragraphe><Paragraphe>Consultez la notification des résultats pour savoir à quel tribunal adresser votre demande.</Paragraphe><OuSAdresser ID="R30" sve="non" type="Local"><Titre>Tribunal judiciaire</Titre><RessourceWeb URL="http://www.annuaires.justice.gouv.fr/"/><Source ID="R30663">Ministère chargé de la justice</Source></OuSAdresser></Complement></SousChapitre></Chapitre><Chapitre><Titre><Paragraphe>Drogue au volant : quelles sanctions ?</Paragraphe></Titre><Paragraphe>Vous pouvez utiliser un <MiseEnEvidence>simulateur</MiseEnEvidence> pour savoir quelle sanction vous risquez en cas d'infraction routière :</Paragraphe><ServiceEnLigne ID="R53432" URL="https://www.service-public.fr/simulateur/calcul/Infraction" audience="Particuliers" type="Simulateur"><Titre>Que risque-t-on en cas d'infraction routière ?</Titre><Source ID="R30608">Direction de l'information légale et administrative (Dila) - Premier ministre</Source></ServiceEnLigne><Paragraphe>Si vous conduisez après avoir consommé de la drogue, vous risquez jusqu'à <MiseEnEvidence>2 ans de prison</MiseEnEvidence> et <Valeur>4 500 €</Valeur> d'amende.</Paragraphe><Paragraphe>En cas <LienInterne LienPublication="F2881" type="Fiche d'information conditionnée" audience="Particuliers">d'alcoolémie positive</LienInterne>, vous risquez jusqu'à <MiseEnEvidence>3 ans de prison</MiseEnEvidence> et <Valeur>9 000 €</Valeur> d'amende.</Paragraphe><Paragraphe>Votre véhicule peut être <LienInterne LienPublication="F12914" type="Fiche d'information conditionnée" audience="Particuliers">immobilisé</LienInterne>.</Paragraphe><Paragraphe><MiseEnEvidence>6 points</MiseEnEvidence> sont retirés de votre permis de conduire.</Paragraphe><Paragraphe>Vous risquez également les <LienIntra LienID="R2515" type="Définition de glossaire">peines complémentaires</LienIntra> suivantes :</Paragraphe><Liste type="puce"><Item><Paragraphe><LienInterne LienPublication="F21761" type="Fiche d'information conditionnée" audience="Particuliers">Suspension du permis</LienInterne> pour une durée de 3 ans au plus (sans aménagement possible en dehors de l'activité professionnelle)</Paragraphe></Item><Item><Paragraphe><LienInterne LienPublication="F21774" type="Fiche d'information conditionnée" audience="Particuliers">Annulation</LienInterne> du permis et 3 ans maximum d'interdiction de demander un nouveau permis</Paragraphe></Item><Item><Paragraphe>Peine de <LienInterne LienPublication="F1407" type="Fiche d'information conditionnée" audience="Particuliers">travail d'intérêt général</LienInterne></Paragraphe></Item><Item><Paragraphe>Peine de <LienIntra LienID="R51093" type="Définition de glossaire">jours-amende</LienIntra></Paragraphe></Item><Item><Paragraphe>Interdiction de conduire certains véhicules, y compris les véhicules sans permis, pour une durée de 5 ans au plus</Paragraphe></Item><Item><Paragraphe>Obligation d'accomplir, à vos frais, un <LienInterne LienPublication="F14208" type="Fiche d'information conditionnée" audience="Particuliers">stage de sensibilisation à la sécurité routière</LienInterne></Paragraphe></Item><Item><Paragraphe>Obligation d'accomplir, à vos frais, un stage de sensibilisation aux dangers de l'usage de produits stupéfiants</Paragraphe></Item><Item><Paragraphe><LienInterne LienPublication="F21887" type="Fiche d'information conditionnée" audience="Particuliers">Confiscation de votre véhicule</LienInterne></Paragraphe></Item></Liste><Attention><Titre>Attention</Titre><Paragraphe>En cas de test de dépistage positif, <MiseEnEvidence>refuser de vous soumettre aux vérifications</MiseEnEvidence> entraîne les <MiseEnEvidence>mêmes sanctions</MiseEnEvidence>.</Paragraphe></Attention><Complement><Titre>Connaître les sanctions encourus si vous êtes responsable d'un accident</Titre><Paragraphe>La <MiseEnEvidence>conduite après usage de drogues</MiseEnEvidence> est une <MiseEnEvidence>circonstance aggravante</MiseEnEvidence> en cas d'accident.</Paragraphe><Paragraphe>Lorsqu'il y a <MiseEnEvidence>2 circonstances aggravantes ou plus</MiseEnEvidence> (par exemple, usage de drogues + alcool), vous risquez :</Paragraphe><Liste type="puce"><Item><Paragraphe>Jusqu'à <MiseEnEvidence>7 ans de prison</MiseEnEvidence> et <Valeur>100 000 €</Valeur> d'amende si vous êtes responsable d'un accident corporel (blessures).</Paragraphe></Item><Item><Paragraphe>Jusqu'à <MiseEnEvidence>10 ans de prison</MiseEnEvidence> et <Valeur>150 000 €</Valeur> d'amende si vous êtes responsable d'un accident mortel.</Paragraphe></Item></Liste></Complement><Complement><Titre>Connaître les sanctions encourus en cas de récidive</Titre><Paragraphe>En cas de <LienIntra LienID="R731" type="Définition de glossaire">récidive</LienIntra>, votre véhicule est <LienInterne LienPublication="F21887" type="Fiche d'information conditionnée" audience="Particuliers">confisqué</LienInterne> et votre permis de conduire est <LienInterne LienPublication="F21774" type="Fiche d'information conditionnée" audience="Particuliers">annulé</LienInterne>. Vous avez l'interdiction de demander un nouveau permis de conduire pendant 3 ans maximum.</Paragraphe></Complement></Chapitre><Chapitre><Titre><Paragraphe>Accident sous l'effet de drogues : quelle conséquence sur votre assurance ?</Paragraphe></Titre><Paragraphe>En cas <MiseEnEvidence>d'accident après usage de drogues</MiseEnEvidence>, votre <MiseEnEvidence>compagnie d'assurance</MiseEnEvidence> vous appliquera des <LienInterne LienPublication="F2630" type="Fiche Question-réponse conditionnée" audience="Particuliers">sanctions</LienInterne> (augmentation des cotisations, résiliation du contrat…).</Paragraphe></Chapitre></Texte><VoirAussi important="non"><Dossier ID="N18918" audience="Particuliers"><Titre>Infractions routières</Titre><Theme ID="N19812"><Titre>Transports - Mobilité</Titre></Theme></Dossier><Dossier ID="N530" audience="Particuliers"><Titre>Permis de conduire</Titre><Theme ID="N19812"><Titre>Transports - Mobilité</Titre></Theme></Dossier><Dossier ID="N275" audience="Particuliers"><Titre>Condamnations et peines</Titre><Theme ID="N19807"><Titre>Justice</Titre></Theme></Dossier><Fiche ID="F2881" audience="Particuliers"><Titre>Alcool au volant</Titre><Theme ID="N19812"><Titre>Transports - Mobilité</Titre></Theme></Fiche><Fiche ID="F19460" audience="Particuliers"><Titre>Vitesse au volant </Titre><Theme ID="N19812"><Titre>Transports - Mobilité</Titre></Theme></Fiche><Fiche ID="F740" audience="Particuliers"><Titre>Traitement de la toxicomanie</Titre><Theme ID="N19811"><Titre>Social - Santé</Titre></Theme></Fiche><Fiche ID="F14710" audience="Particuliers"><Titre>Casier judiciaire : présentation des trois bulletins</Titre><Theme ID="N19807"><Titre>Justice</Titre></Theme></Fiche></VoirAussi><QuiPeutMAider ID="R20696" sve="non" type="Centre de contact"><Titre>Drogues info service</Titre><Source ID="R30662">Ministère chargé de la santé</Source><Texte><Chapitre><Titre><Paragraphe>Par téléphone</Paragraphe></Titre><Paragraphe><MiseEnEvidence>0 800 23 13 13</MiseEnEvidence> (appel gratuit et anonyme)</Paragraphe><Paragraphe>Ouvert de 8h à 2h, 7 jours/7</Paragraphe><Paragraphe>Informations sur les drogues, l'alcool, les dépendances y compris la dépendance aux jeux.</Paragraphe><Paragraphe>Écoute, soutien, conseils et orientations.</Paragraphe><Paragraphe>Vous pouvez appeler que vous soyez concerné <MiseEnEvidence>directement ou indirectement </MiseEnEvidence>par une consommation de drogues.</Paragraphe></Chapitre><Chapitre><Titre><Paragraphe>Par internet</Paragraphe></Titre><Paragraphe>Accès à <LienExterne URL="http://www.drogues-info-service.fr/?-Vos-questions-nos-reponses-">la rubrique Vos questions / Nos réponses</LienExterne> pour poser des questions aux professionnels du service</Paragraphe></Chapitre><Chapitre><Titre><Paragraphe>Par chat</Paragraphe></Titre><Paragraphe>Ouvert :</Paragraphe><Liste type="puce"><Item><Paragraphe>De 14h à minuit du lundi au vendredi</Paragraphe></Item><Item><Paragraphe>Et de 14h à 20h le samedi et le dimanche.</Paragraphe><Paragraphe><LienExterne URL="https://www.drogues-info-service.fr/Drogues/Chat">https://www.drogues-info-service.fr/Drogues/Chat</LienExterne></Paragraphe></Item></Liste></Chapitre></Texte></QuiPeutMAider><QuiPeutMAider ID="R11621" sve="non" type="Local personnalisé sur SP"><Titre>Maison de justice et du droit</Titre><PivotLocal>mjd</PivotLocal><RessourceWeb URL="http://www.annuaires.justice.gouv.fr/lieux-dacces-aux-droits-10111/"/><Source ID="R30663">Ministère chargé de la justice</Source></QuiPeutMAider><Reference type="Texte de référence" URL="https://www.legifrance.gouv.fr/codes/section_lc/LEGITEXT000006074228/LEGISCTA000006159522" ID="R34836"><Titre>Code de la route : articles L235-1 à L235-5</Titre><Complement>Conduite après usage de substances ou plantes classées comme stupéfiants</Complement></Reference><Reference type="Texte de référence" URL="https://www.legifrance.gouv.fr/codes/id/LEGISCTA000006177151/" ID="R46207"><Titre>Code de la route : articles R235-3 à R235-4</Titre><Complement>Épreuves de dépistage</Complement></Reference><Reference type="Texte de référence" URL="https://www.legifrance.gouv.fr/codes/id/LEGISCTA000006177152/" ID="R52331"><Titre>Code de la route : articles R235-5 à R235-11</Titre><Complement>Analyses et examens médicaux, cliniques et biologiques</Complement></Reference><Reference type="Texte de référence" URL="https://www.legifrance.gouv.fr/codes/section_lc/LEGITEXT000006070719/LEGISCTA000006165277/#LEGISCTA000006165277" ID="R50381"><Titre>Code pénal : articles 221-6 à 221-7</Titre><Complement>Peines encourues en cas d'atteinte involontaires à la vie</Complement></Reference><Reference type="Texte de référence" URL="https://www.legifrance.gouv.fr/codes/section_lc/LEGITEXT000006070719/LEGISCTA000006165280/" ID="R50382"><Titre>Code pénal : articles 222-19 à 222-21</Titre><Complement>Peines encourues en cas d'atteinte involontaire à l'intégrité de la personne</Complement></Reference><Reference type="Texte de référence" URL="https://www.legifrance.gouv.fr/loda/id/JORFTEXT000000533085/" ID="R52330"><Titre>Arrêté du 22 février 1990 fixant la liste des substances classées comme stupéfiants</Titre></Reference><Reference type="Texte de référence" URL="https://www.legifrance.gouv.fr/loda/id/JORFTEXT000033607271/" ID="R46208"><Titre>Arrêté du 13 décembre 2016 fixant les modalités du dépistage des substances témoignant de l'usage de stupéfiants</Titre></Reference><ServiceEnLigne ID="R53432" URL="https://www.service-public.fr/simulateur/calcul/Infraction" audience="Particuliers" type="Simulateur"><Titre>Que risque-t-on en cas d'infraction routière ?</Titre><Source ID="R30608">Direction de l'information légale et administrative (Dila) - Premier ministre</Source></ServiceEnLigne><ServiceEnLigne ID="R17121" URL="https://mespoints.permisdeconduire.gouv.fr" audience="Particuliers" type="Téléservice"><Titre>Permis de conduire : consulter ses points et ses relevés</Titre><Source ID="R30603">Ministère chargé de l'intérieur</Source></ServiceEnLigne><PourEnSavoirPlus type="Information pratique" ID="R52333" URL="https://www.legifrance.gouv.fr/loda/id/JORFTEXT000000533085" audience="Particuliers"><Titre>Substances classées comme stupéfiants</Titre><Source ID="R38880">Legifrance</Source></PourEnSavoirPlus><PourEnSavoirPlus type="Information pratique" ID="R14783" URL="http://www.drogues-info-service.fr/" audience="Particuliers"><Titre>Drogues info service</Titre><Source ID="R30644">Santé publique France</Source></PourEnSavoirPlus><PourEnSavoirPlus type="Information pratique" ID="R41572" URL="http://www.drogues.gouv.fr/" audience="Particuliers"><Titre>Drogues.gouv.fr</Titre><Source ID="R30860">Mission interministérielle de lutte contre les drogues et les conduites addictives (Mildeca)</Source></PourEnSavoirPlus><PourEnSavoirPlus type="Information pratique" ID="R41622" URL="http://www.securite-routiere.gouv.fr" audience="Particuliers"><Titre>Site de la sécurité routière</Titre><Source ID="R30603">Ministère chargé de l'intérieur</Source></PourEnSavoirPlus><Definition ID="R52094"><Titre>Infraction</Titre><Texte><Paragraphe>Acte ou comportement interdit par la loi et puni par une peine</Paragraphe></Texte></Definition><Definition ID="R1123"><Titre>Procureur de la République</Titre><Texte><Paragraphe>Magistrat à la tête du parquet (ou ministère public). Il est destinataire des plaintes et signalements. Il dirige les enquêtes, décide des poursuites et veille à l'application de la loi.</Paragraphe></Texte></Definition><Definition ID="R14732"><Titre>Notification</Titre><Texte><Paragraphe>Formalité par laquelle un acte de procédure ou une décision est porté à la connaissance d’une personne</Paragraphe></Texte></Definition><Definition ID="R2515"><Titre>Peine complémentaire</Titre><Texte><Paragraphe>Sanction qui peut s'ajouter à une peine principale de prison ou d'amende. Exemples : privation des droits civiques (droit de vote et éligibilité...), obligation de soins, retrait du permis de conduire.</Paragraphe></Texte></Definition><Definition ID="R51093"><Titre>Jour-amende</Titre><Texte><Paragraphe>Peine consistant pour le condamné à verser au Trésor une somme. Son montant global résulte de la fixation par le juge d'une contribution quotidienne pendant un certain nombre de jours.</Paragraphe></Texte><Reference type="Texte de référence" URL="https://www.legifrance.gouv.fr/codes/section_lc/LEGITEXT000006070719/LEGISCTA000006181728" ID="R35923"><Titre>Code pénal : articles 131-3 à 131-9</Titre></Reference></Definition><Definition ID="R731"><Titre>Récidive légale</Titre><Texte><Paragraphe>Fait, pour une personne déjà condamnée, de commettre une nouvelle infraction identique ou assimilée, dans un certain délai, et pouvant entraîner une peine plus lourde que celle normalement prévue.</Paragraphe></Texte></Definition><Abreviation ID="R65189" type="Sigle"><Titre>LSD</Titre><Texte><Paragraphe>Diéthylamide de l'acide lysergique</Paragraphe></Texte></Abreviation><QuestionReponse ID="F2630" audience="Particuliers"><Titre>Accident sous l'effet d'alcool ou de drogue : quelles conséquences sur l'assurance ?</Titre></QuestionReponse><QuestionReponse ID="F33341" audience="Particuliers"><Titre>Que risque-t-on pour usage de drogues ?</Titre></QuestionReponse><QuestionReponse ID="F2794" audience="Particuliers"><Titre>Quels papiers du véhicule sont obligatoires lors d'un contrôle routier ?</Titre></QuestionReponse><QuestionReponse ID="F34791" audience="Particuliers"><Titre>Permis de conduire : comment demander un relevé d'information intégral (RII) ?</Titre></QuestionReponse><QuestionReponse ID="F17970" audience="Particuliers"><Titre>Solde du permis de conduire : comment connaître son nombre de points ?</Titre></QuestionReponse></Publication>