<?xml version="1.0" encoding="UTF-8"?><ServiceComplementaire xmlns:dc="http://purl.org/dc/elements/1.1/" xmlns:xsi="http://www.w3.org/2001/XMLSchema-instance" ID="R61073" type="Formulaire" xsi:noNamespaceSchemaLocation="../Schemas/3.4/ServiceComplementaire.xsd" spUrl="https://www.service-public.fr/particuliers/vosdroits/R61073"><dc:title>Certificat médical de contre-indication à la vaccination COVID-19 (Formulaire 16183*02)</dc:title><dc:creator>Direction de l'information légale et administrative</dc:creator><dc:description>Certificat médical de contre-indication à la vaccination COVID-19 - Formulaire</dc:description><dc:publisher>Direction de l'information légale et administrative</dc:publisher><dc:contributor>Direction de l'information légale et administrative (Premier ministre)</dc:contributor><dc:date>modified 2021-12-16</dc:date><dc:type>Formulaire</dc:type><dc:format>text/xml</dc:format><dc:identifier>R61073</dc:identifier><dc:language>Fr</dc:language><dc:coverage>France entière</dc:coverage><dc:rights>https://www.service-public.fr/a-propos/mentions-legales</dc:rights><SurTitre>Formulaire</SurTitre><Audience>Particuliers</Audience><Canal>www.service-public.fr</Canal><FilDAriane><Niveau ID="Particuliers">Accueil particuliers</Niveau><Niveau ID="servicesEnLigne" type="Liste - Service en ligne">Services en ligne et formulaires</Niveau><Niveau ID="R61073" type="Formulaire">Certificat médical de contre-indication à la vaccination COVID-19</Niveau></FilDAriane><NumeroCerfa>16183*02</NumeroCerfa><LienWeb URL="https://www.formulaires.service-public.fr/gf/cerfa_16183.do" format="application/force-download" poids="254.9 KB"><Source>Ministère chargé de la santé</Source></LienWeb></ServiceComplementaire>